AUTHORS
LICENSE
MANIFEST.in
README.rst
requirements.txt
setup.py
openslides_export/__init__.py
openslides_export/main_menu.py
openslides_export/models.py
openslides_export/signals.py
openslides_export/urls.py
openslides_export/views.py
openslides_export.egg-info/PKG-INFO
openslides_export.egg-info/SOURCES.txt
openslides_export.egg-info/dependency_links.txt
openslides_export.egg-info/entry_points.txt
openslides_export.egg-info/requires.txt
openslides_export.egg-info/top_level.txt
openslides_export/locale/README.txt
openslides_export/locale/de/LC_MESSAGES/django.mo
openslides_export/locale/de/LC_MESSAGES/django.po
openslides_export/static/css/openslides_export.css
openslides_export/static/img/glyphicons_359_file_export.png
openslides_export/static/img/glyphicons_359_file_export_white.png
openslides_export/templates/openslides_export/export_list.html
openslides_export/templates/openslides_export/template-motion-list.html
openslides_export/templates/openslides_export/template-motion-list.odt
openslides_export/templates/openslides_export/template-motion.html
openslides_export/templates/openslides_export/template-motion.odt