Metadata-Version: 1.1
Name: openslides-export
Version: 1.0
Summary: OpenSlides Export Plugin
Home-page: https://github.com/OpenSlides/openslides-export
Author: Authors of OpenSlides Export Plugin, see AUTHORS
Author-email: support@openslides.org
License: MIT
Keywords: OpenSlides
Platform: UNKNOWN
Classifier: Development Status :: 5 - Production/Stable
Classifier: Environment :: Plugins
Classifier: Environment :: Web Environment
Classifier: Framework :: Django
Classifier: License :: OSI Approved :: MIT License
Classifier: Operating System :: OS Independent
Classifier: Programming Language :: Python :: 2
